spider_ai/__init__.py
spider_ai/setup.py
spider_ai-1.0.dist-info/METADATA
spider_ai-1.0.dist-info/WHEEL
spider_ai-1.0.dist-info/top_level.txt
spider_ai-1.0.dist-info/RECORD
