Metadata-Version: 2.1
Name: spider-ai
Version: 1.0
Summary: lib python for AI
Author: spiderXR
License: MIT
Keywords: spider-ai
Classifier: Development Status :: 5 - Production/Stable
Classifier: Intended Audience :: Education
Classifier: Operating System :: Microsoft :: Windows :: Windows 10
Classifier: License :: OSI Approved :: MIT License
Classifier: Programming Language :: Python :: 3
